keyed_extras/__init__.py
keyed_extras-0.0.1.dist-info/METADATA
keyed_extras-0.0.1.dist-info/WHEEL
keyed_extras-0.0.1.dist-info/top_level.txt
keyed_extras-0.0.1.dist-info/RECORD
