Metadata-Version: 2.4
Name: keyed-extras
Version: 0.0.1
Summary: Placeholder package for keyed-extras sponsorware
Author-email: Doug Mercer <dougmerceryt@gmail.com>
Project-URL: Homepage, https://dougmercer.github.io/keyed/extras/
Keywords: keyed,animation,reactive,sponsorware,placeholder
Classifier: Development Status :: 4 - Beta
Classifier: Intended Audience :: Developers
Classifier: Programming Language :: Python :: 3.11
Classifier: Programming Language :: Python :: 3.12
Requires-Python: >=3.11
